linkrot/__init__.py
linkrot/archive.py
linkrot/backends.py
linkrot/cli.py
linkrot/colorprint.py
linkrot/downloader.py
linkrot/exceptions.py
linkrot/extractor.py
linkrot/retraction.py
linkrot/threadpool.py
linkrot/libs/__init__.py
linkrot/libs/xmp.py
linkrot-5.2.2.dist-info/METADATA
linkrot-5.2.2.dist-info/WHEEL
linkrot-5.2.2.dist-info/entry_points.txt
linkrot-5.2.2.dist-info/licenses/LICENSE
linkrot-5.2.2.dist-info/RECORD
