Metadata-Version: 2.4
Name: linkrot
Version: 5.2.2
Summary: Extract metadata and URLs from PDF files
Project-URL: Homepage, https://github.com/rottingresearch/linkrot
Author-email: Marshal Miller <marshal@rottingresearch.org>
License-Expression: GPL-3.0-or-later
License-File: LICENSE
Keywords: linkrot,pdf,reference
Classifier: Development Status :: 5 - Production/Stable
Classifier: Environment :: Console
Classifier: Programming Language :: Python :: 3.8
Classifier: Programming Language :: Python :: 3.9
Classifier: Programming Language :: Python :: 3.10
Classifier: Programming Language :: Python :: 3.11
Classifier: Programming Language :: Python :: 3.12
Classifier: Programming Language :: Python :: 3.13
Classifier: Topic :: Scientific/Engineering
Classifier: Topic :: Software Development :: Build Tools
Classifier: Topic :: Software Development :: Libraries
Classifier: Topic :: Utilities
Requires-Python: >=3.8
Requires-Dist: chardet==5.2.0
Requires-Dist: lxml==6.0.0
Requires-Dist: pymupdf==1.26.3
Requires-Dist: requests>=2.25.0
Provides-Extra: dev
Requires-Dist: black==25.1.0; extra == 'dev'
Requires-Dist: build==1.2.2.post1; extra == 'dev'
Requires-Dist: coverage==7.9.2; extra == 'dev'
Requires-Dist: flake8==7.3.0; extra == 'dev'
Requires-Dist: mccabe<=0.7.0; extra == 'dev'
Requires-Dist: mega-py==1.0.8; extra == 'dev'
Requires-Dist: mypy==1.17.0; extra == 'dev'
Requires-Dist: pylint==3.3.7; extra == 'dev'
Requires-Dist: pytest==8.4.1; extra == 'dev'
Provides-Extra: test
Requires-Dist: mega-py==1.0.8; extra == 'test'
Requires-Dist: pytest==8.4.1; extra == 'test'
